CMA/__init__.py
CMA/api.py
CMA/cli.py
CMA/utils.py
ClevelandMuseumArt-1.0.1.dist-info/LICENSE
ClevelandMuseumArt-1.0.1.dist-info/METADATA
ClevelandMuseumArt-1.0.1.dist-info/WHEEL
ClevelandMuseumArt-1.0.1.dist-info/entry_points.txt
ClevelandMuseumArt-1.0.1.dist-info/top_level.txt
ClevelandMuseumArt-1.0.1.dist-info/RECORD
