Metadata-Version: 2.1
Name: ClevelandMuseumArt
Version: 1.0.1
Summary: Python wrapper for Cleveland Museum of Art Open Access API
Home-page: https://github.com/WTFender/CMA
Author: Michael McIntyre
Author-email: wtfender.cs@gmail.com
License: UNKNOWN
Platform: UNKNOWN
Classifier: Programming Language :: Python :: 3
Classifier: Operating System :: OS Independent
Requires-Dist: numpy (==1.19.5)
Requires-Dist: pillow (==8.1.0)
Requires-Dist: requests (==2.25.1)
